CODE_OF_CONDUCT.md
LICENSE
MANIFEST.in
README.md
setup.cfg
setup.py
versioneer.py
idptools_pipit.egg-info/PKG-INFO
idptools_pipit.egg-info/SOURCES.txt
idptools_pipit.egg-info/dependency_links.txt
idptools_pipit.egg-info/top_level.txt
pipit/.DS_Store
pipit/__init__.py
pipit/_version.py
pipit/backend.py
pipit/shuffle.py
pipit/backend/.DS_Store
pipit/data/README.md
pipit/data/look_and_say.dat
pipit/tests/__init__.py
pipit/tests/test_pipit.py
scripts/pipit-shuffle