Metadata-Version: 2.1
Name: idptools-pipit
Version: 1.2
Summary: UNKNOWN
Home-page: UNKNOWN
Author: Ryan Emenecker Washington University School of Medicine
Author-email: remenecker@wustl.edu
License: MIT
Platform: UNKNOWN
Requires-Python: >=3.5
